{
  "version": "0.4.36",
  "flags": {},
  "shapes": [
    {
      "label": "bot",
      "text": "",
      "points": [
        [
          1035.0,
          140.625
        ],
        [
          1152.5,
          315.625
        ]
      ],
      "group_id": null,
      "shape_type": "rectangle",
      "flags": {}
    },
    {
      "label": "bot",
      "text": "",
      "points": [
        [
          1321.25,
          110.625
        ],
        [
          1432.5,
          238.125
        ]
      ],
      "group_id": null,
      "shape_type": "rectangle",
      "flags": {}
    },
    {
      "label": "ball",
      "text": "",
      "points": [
        [
          1482.5,
          185.625
        ],
        [
          1506.25,
          208.125
        ]
      ],
      "group_id": null,
      "shape_type": "rectangle",
      "flags": {}
    }
  ],
  "imagePath": "IMG_9866_f00091.jpg",
  "imageData": null,
  "imageHeight": 1080,
  "imageWidth": 1920
}